{
    "1662572007592707230": {
        "acceleration": {
            "x": 0.001953125,
            "y": 0.0,
            "z": 1.00341796875
        }
    },
    "1662572007592744786": {
        "acceleration": {
            "x": 0.001953125,
            "y": 0.0,
            "z": 1.00341796875
        }
    },
    "1662572007606836245": {
        "acceleration": {
            "x": 0.001953125,
            "y": 0.0,
            "z": 1.00341796875
        }
    },
    "1662572007606863240": {
        "acceleration": {
            "x": 0.001953125,
            "y": 0.0,
            "z": 1.00341796875
        }
    },
    "1662572007642343882": {
        "acceleration": {
            "x": 0.00244140625,
            "y": 0.0,
            "z": 1.0029296875
        }
    },
    "1662572007642359653": {
        "acceleration": {
            "x": 0.00244140625,
            "y": 0.0,
            "z": 1.0029296875
        }
    },
    "1662572007656741764": {
        "acceleration": {
            "x": 0.00244140625,
            "y": 0.0,
            "z": 1.0029296875
        }
    },
    "1662572007656760673": {
        "acceleration": {
            "x": 0.00244140625,
            "y": 0.0,
            "z": 1.0029296875
        }
    },
    "1662572007693320609": {
        "acceleration": {
            "x": -0.02294921875,
            "y": -0.26513671875,
            "z": 1.015625
        }
    },
    "1662572007693337199": {
        "acceleration": {
            "x": -0.02294921875,
            "y": -0.26513671875,
            "z": 1.015625
        }
    },
    "1662572007707223691": {
        "acceleration": {
            "x": -0.02294921875,
            "y": -0.26513671875,
            "z": 1.015625
        }
    },
    "1662572007707247267": {
        "acceleration": {
            "x": -0.02294921875,
            "y": -0.26513671875,
            "z": 1.015625
        }
    },
    "1662572007742356306": {
        "acceleration": {
            "x": 0.01171875,
            "y": -0.0625,
            "z": 1.00390625
        }
    },
    "1662572007742376534": {
        "acceleration": {
            "x": 0.01171875,
            "y": -0.0625,
            "z": 1.00390625
        }
    },
    "1662572007756485981": {
        "acceleration": {
            "x": 0.01171875,
            "y": -0.0625,
            "z": 1.00390625
        }
    },
    "1662572007756533206": {
        "acceleration": {
            "x": 0.01171875,
            "y": -0.0625,
            "z": 1.00390625
        }
    },
    "1662572007792073787": {
        "acceleration": {
            "x": 0.0068359375,
            "y": -0.05322265625,
            "z": 1.00830078125
        }
    },
    "1662572007792100635": {
        "acceleration": {
            "x": 0.0068359375,
            "y": -0.05322265625,
            "z": 1.00830078125
        }
    },
    "1662572007807198122": {
        "acceleration": {
            "x": 0.0068359375,
            "y": -0.05322265625,
            "z": 1.00830078125
        }
    },
    "1662572007807234855": {
        "acceleration": {
            "x": 0.0068359375,
            "y": -0.05322265625,
            "z": 1.00830078125
        }
    },
    "1662572007842892190": {
        "acceleration": {
            "x": 0.005859375,
            "y": -0.0263671875,
            "z": 1.001953125
        }
    },
    "1662572007842907521": {
        "acceleration": {
            "x": 0.005859375,
            "y": -0.0263671875,
            "z": 1.001953125
        }
    },
    "1662572007856935527": {
        "acceleration": {
            "x": 0.005859375,
            "y": -0.0263671875,
            "z": 1.001953125
        }
    },
    "1662572007856965350": {
        "acceleration": {
            "x": 0.005859375,
            "y": -0.0263671875,
            "z": 1.001953125
        }
    },
    "1662572007891647097": {
        "acceleration": {
            "x": 0.0,
            "y": -0.005859375,
            "z": 0.99365234375
        }
    },
    "1662572007891662498": {
        "acceleration": {
            "x": 0.0,
            "y": -0.005859375,
            "z": 0.99365234375
        }
    },
    "1662572007906959423": {
        "acceleration": {
            "x": 0.0,
            "y": -0.005859375,
            "z": 0.99365234375
        }
    },
    "1662572007906997157": {
        "acceleration": {
            "x": 0.0,
            "y": -0.005859375,
            "z": 0.99365234375
        }
    },
    "1662572007941528549": {
        "acceleration": {
            "x": -0.001953125,
            "y": -0.015625,
            "z": 1.005859375
        }
    },
    "1662572007941545637": {
        "acceleration": {
            "x": -0.001953125,
            "y": -0.015625,
            "z": 1.005859375
        }
    },
    "1662572007956808954": {
        "acceleration": {
            "x": -0.001953125,
            "y": -0.015625,
            "z": 1.005859375
        }
    },
    "1662572007956836571": {
        "acceleration": {
            "x": -0.001953125,
            "y": -0.015625,
            "z": 1.005859375
        }
    },
    "1662572007991677985": {
        "acceleration": {
            "x": 0.00537109375,
            "y": 0.01318359375,
            "z": 1.005859375
        }
    },
    "1662572007992026342": {
        "acceleration": {
            "x": 0.00537109375,
            "y": 0.01318359375,
            "z": 1.005859375
        }
    },
    "1662572008006139451": {
        "acceleration": {
            "x": 0.00537109375,
            "y": 0.01318359375,
            "z": 1.005859375
        }
    },
    "1662572008006163910": {
        "acceleration": {
            "x": 0.00537109375,
            "y": 0.01318359375,
            "z": 1.005859375
        }
    },
    "1662572008041476385": {
        "acceleration": {
            "x": -0.00048828125,
            "y": 0.02197265625,
            "z": 1.005859375
        }
    },
    "1662572008041505125": {
        "acceleration": {
            "x": -0.00048828125,
            "y": 0.02197265625,
            "z": 1.005859375
        }
    },
    "1662572008056478301": {
        "acceleration": {
            "x": -0.00048828125,
            "y": 0.02197265625,
            "z": 1.005859375
        }
    },
    "1662572008056502136": {
        "acceleration": {
            "x": -0.00048828125,
            "y": 0.02197265625,
            "z": 1.005859375
        }
    },
    "1662572008090889291": {
        "acceleration": {
            "x": 0.0,
            "y": 0.03515625,
            "z": 1.0029296875
        }
    },
    "1662572008090907112": {
        "acceleration": {
            "x": 0.0,
            "y": 0.03515625,
            "z": 1.0029296875
        }
    },
    "1662572008105934100": {
        "acceleration": {
            "x": 0.0,
            "y": 0.03515625,
            "z": 1.0029296875
        }
    },
    "1662572008105963372": {
        "acceleration": {
            "x": 0.0,
            "y": 0.03515625,
            "z": 1.0029296875
        }
    },
    "1662572008141741971": {
        "acceleration": {
            "x": 0.00146484375,
            "y": 0.04833984375,
            "z": 1.01220703125
        }
    },
    "1662572008141760666": {
        "acceleration": {
            "x": 0.00146484375,
            "y": 0.04833984375,
            "z": 1.01220703125
        }
    },
    "1662572008155702529": {
        "acceleration": {
            "x": 0.00146484375,
            "y": 0.04833984375,
            "z": 1.01220703125
        }
    },
    "1662572008155728236": {
        "acceleration": {
            "x": 0.00146484375,
            "y": 0.04833984375,
            "z": 1.01220703125
        }
    },
    "1662572008191272443": {
        "acceleration": {
            "x": -0.00439453125,
            "y": 0.0693359375,
            "z": 1.00048828125
        }
    },
    "1662572008191293257": {
        "acceleration": {
            "x": -0.00439453125,
            "y": 0.0693359375,
            "z": 1.00048828125
        }
    },
    "1662572008205257768": {
        "acceleration": {
            "x": -0.00439453125,
            "y": 0.0693359375,
            "z": 1.00048828125
        }
    },
    "1662572008205294035": {
        "acceleration": {
            "x": -0.00439453125,
            "y": 0.0693359375,
            "z": 1.00048828125
        }
    },
    "1662572008240900029": {
        "acceleration": {
            "x": 0.001953125,
            "y": 0.046875,
            "z": 1.00146484375
        }
    },
    "1662572008240917251": {
        "acceleration": {
            "x": 0.001953125,
            "y": 0.046875,
            "z": 1.00146484375
        }
    },
    "1662572008254930480": {
        "acceleration": {
            "x": 0.001953125,
            "y": 0.046875,
            "z": 1.00146484375
        }
    },
    "1662572008254954507": {
        "acceleration": {
            "x": 0.001953125,
            "y": 0.046875,
            "z": 1.00146484375
        }
    },
    "1662572008290537698": {
        "acceleration": {
            "x": 0.0029296875,
            "y": 0.09033203125,
            "z": 1.00537109375
        }
    },
    "1662572008290555785": {
        "acceleration": {
            "x": 0.0029296875,
            "y": 0.09033203125,
            "z": 1.00537109375
        }
    },
    "1662572008305611625": {
        "acceleration": {
            "x": 0.0029296875,
            "y": 0.09033203125,
            "z": 1.00537109375
        }
    },
    "1662572008305631713": {
        "acceleration": {
            "x": 0.0029296875,
            "y": 0.09033203125,
            "z": 1.00537109375
        }
    },
    "1662572008340074693": {
        "acceleration": {
            "x": -0.00390625,
            "y": 0.068359375,
            "z": 1.0009765625
        }
    },
    "1662572008340097144": {
        "acceleration": {
            "x": -0.00390625,
            "y": 0.068359375,
            "z": 1.0009765625
        }
    },
    "1662572008355307067": {
        "acceleration": {
            "x": -0.00390625,
            "y": 0.068359375,
            "z": 1.0009765625
        }
    },
    "1662572008355327553": {
        "acceleration": {
            "x": -0.00390625,
            "y": 0.068359375,
            "z": 1.0009765625
        }
    },
    "1662572008390806154": {
        "acceleration": {
            "x": -0.0029296875,
            "y": 0.04345703125,
            "z": 0.99658203125
        }
    },
    "1662572008390839775": {
        "acceleration": {
            "x": -0.0029296875,
            "y": 0.04345703125,
            "z": 0.99658203125
        }
    },
    "1662572008405082871": {
        "acceleration": {
            "x": -0.0029296875,
            "y": 0.04345703125,
            "z": 0.99658203125
        }
    },
    "1662572008405104781": {
        "acceleration": {
            "x": -0.0029296875,
            "y": 0.04345703125,
            "z": 0.99658203125
        }
    },
    "1662572008440704732": {
        "acceleration": {
            "x": -0.01513671875,
            "y": 0.03515625,
            "z": 1.00732421875
        }
    },
    "1662572008440734281": {
        "acceleration": {
            "x": -0.01513671875,
            "y": 0.03515625,
            "z": 1.00732421875
        }
    },
    "1662572008454638637": {
        "acceleration": {
            "x": -0.01513671875,
            "y": 0.03515625,
            "z": 1.00732421875
        }
    },
    "1662572008454662228": {
        "acceleration": {
            "x": -0.01513671875,
            "y": 0.03515625,
            "z": 1.00732421875
        }
    },
    "1662572008489973646": {
        "acceleration": {
            "x": 0.0009765625,
            "y": 0.0107421875,
            "z": 1.01025390625
        }
    },
    "1662572008490001133": {
        "acceleration": {
            "x": 0.0009765625,
            "y": 0.0107421875,
            "z": 1.01025390625
        }
    },
    "1662572008503974298": {
        "acceleration": {
            "x": 0.0009765625,
            "y": 0.0107421875,
            "z": 1.01025390625
        }
    },
    "1662572008503994186": {
        "acceleration": {
            "x": 0.0009765625,
            "y": 0.0107421875,
            "z": 1.01025390625
        }
    },
    "1662572008539451876": {
        "acceleration": {
            "x": 0.00244140625,
            "y": 0.0087890625,
            "z": 0.9970703125
        }
    },
    "1662572008539484677": {
        "acceleration": {
            "x": 0.00244140625,
            "y": 0.0087890625,
            "z": 0.9970703125
        }
    },
    "1662572008554597807": {
        "acceleration": {
            "x": 0.00244140625,
            "y": 0.0087890625,
            "z": 0.9970703125
        }
    },
    "1662572008554619419": {
        "acceleration": {
            "x": 0.00244140625,
            "y": 0.0087890625,
            "z": 0.9970703125
        }
    },
    "1662572008590022114": {
        "acceleration": {
            "x": 0.0078125,
            "y": 0.0302734375,
            "z": 1.00244140625
        }
    },
    "1662572008590044887": {
        "acceleration": {
            "x": 0.0078125,
            "y": 0.0302734375,
            "z": 1.00244140625
        }
    },
    "1662572007532653203": {
        "pose": {
            "position": {
                "x": 3.932039878880763e-17,
                "y": -3.124702353924872e-35,
                "z": -7.401486830834377e-17
            },
            "orientation": {
                "x": -1.500581851184342e-19,
                "y": -2.40914070165829e-19,
                "z": -1.1487612279202307e-19,
                "w": 1.0
            }
        }
    },
    "1662572007582832129": {
        "pose": {
            "position": {
                "x": 0.002585910907233769,
                "y": 0.00047222919641459526,
                "z": 7.584773622119154e-05
            },
            "orientation": {
                "x": -0.00022080918687339125,
                "y": 0.0012437299405235135,
                "z": -2.6832185538080837e-05,
                "w": 0.9999992018292673
            }
        }
    },
    "1662572007643213486": {
        "pose": {
            "position": {
                "x": -0.00014261695651572403,
                "y": -0.0004300539583323525,
                "z": -2.3119367265113517e-05
            },
            "orientation": {
                "x": 0.0001404233988490183,
                "y": 6.69246731920302e-06,
                "z": -0.0001559361451640162,
                "w": 0.9999999779601991
            }
        }
    },
    "1662572007693054637": {
        "pose": {
            "position": {
                "x": 0.006213690599605984,
                "y": -0.06710337413342558,
                "z": -0.016176355123601608
            },
            "orientation": {
                "x": 0.03388845935712422,
                "y": 0.004589528000584519,
                "z": 0.0027549707354396777,
                "w": 0.9994112860536343
            }
        }
    },
    "1662572007743422335": {
        "pose": {
            "position": {
                "x": -0.013135412593778227,
                "y": -0.046323973810226265,
                "z": -0.009027575810027747
            },
            "orientation": {
                "x": 0.023510126565536797,
                "y": 0.00023004376000458876,
                "z": 0.0011994783505957386,
                "w": 0.9997228527349106
            }
        }
    },
    "1662572008603983303": {
        "acceleration": {
            "x": 0.0078125,
            "y": 0.0302734375,
            "z": 1.00244140625
        }
    },
    "1662572007783585860": {
        "pose": {
            "position": {
                "x": -0.02369321901760809,
                "y": -0.062339160212677255,
                "z": -0.015919375953116804
            },
            "orientation": {
                "x": 0.031218894490775726,
                "y": -0.0011895014014816673,
                "z": 0.000720141712989478,
                "w": 0.9995116042893663
            }
        }
    },
    "1662572007833845357": {
        "pose": {
            "position": {
                "x": -0.018211826319153555,
                "y": 0.01779561385455695,
                "z": -0.0058339441852105055
            },
            "orientation": {
                "x": -0.00751987824573923,
                "y": 0.0077279729323923955,
                "z": -3.1854922499984486e-05,
                "w": 0.9999418627354237
            }
        }
    },
    "1662572008604012182": {
        "acceleration": {
            "x": 0.0078125,
            "y": 0.0302734375,
            "z": 1.00244140625
        }
    },
    "1662572007883698779": {
        "pose": {
            "position": {
                "x": -0.05645048144369876,
                "y": -0.057984184257516766,
                "z": -0.01897668549511182
            },
            "orientation": {
                "x": 0.02947381774592153,
                "y": -0.005849576441117021,
                "z": 0.0017274853462824122,
                "w": 0.999546943528576
            }
        }
    },
    "1662572007933998367": {
        "pose": {
            "position": {
                "x": -0.04755077654213223,
                "y": 0.032989984853983675,
                "z": -0.006387134325751913
            },
            "orientation": {
                "x": -0.015080166571873431,
                "y": 0.005996140536471033,
                "z": -0.0006973092074044376,
                "w": 0.9998680656140093
            }
        }
    },
    "1662572007984443433": {
        "pose": {
            "position": {
                "x": -0.0570462946117873,
                "y": 0.015954371210243918,
                "z": -0.00541908156692825
            },
            "orientation": {
                "x": -0.006670176543188839,
                "y": 0.0031997022302537245,
                "z": -8.780941011527257e-05,
                "w": 0.9999726310954854
            }
        }
    },
    "1662572008034502109": {
        "pose": {
            "position": {
                "x": -0.09149952218825438,
                "y": -0.05910066838161801,
                "z": -0.02135830018408815
            },
            "orientation": {
                "x": 0.02941576595858347,
                "y": -0.007661469821650579,
                "z": -0.0007591675760685638,
                "w": 0.9995376122276906
            }
        }
    },
    "1662572008074526246": {
        "pose": {
            "position": {
                "x": -0.10666290698702625,
                "y": -0.059606680532674275,
                "z": -0.02361322374718108
            },
            "orientation": {
                "x": 0.02988091047148212,
                "y": -0.010831696444729548,
                "z": -0.0011612324629671725,
                "w": 0.9994941005732308
            }
        }
    },
    "1662572008114470120": {
        "pose": {
            "position": {
                "x": -0.11328955988851583,
                "y": -0.05147790975690016,
                "z": -0.02171798097975939
            },
            "orientation": {
                "x": 0.02576530693643207,
                "y": -0.011160643019249168,
                "z": -0.0004175066994974631,
                "w": 0.9996056295829991
            }
        }
    },
    "1662572008164922609": {
        "pose": {
            "position": {
                "x": -0.11964977237309027,
                "y": -0.04522851060557384,
                "z": -0.020733052529969577
            },
            "orientation": {
                "x": 0.022200905629181495,
                "y": -0.011440233643041111,
                "z": -0.0006967458779751535,
                "w": 0.9996878289689328
            }
        }
    },
    "1662572008214935778": {
        "pose": {
            "position": {
                "x": -0.11349241171926887,
                "y": -0.050129262105304453,
                "z": -0.020267335068184133
            },
            "orientation": {
                "x": 0.024869604270957635,
                "y": -0.0076358070627193225,
                "z": 0.0006143217237353831,
                "w": 0.9996613525803261
            }
        }
    },
    "1662572008275096815": {
        "pose": {
            "position": {
                "x": -0.11771684926627277,
                "y": -0.05562197905042013,
                "z": -0.022433750530764747
            },
            "orientation": {
                "x": 0.027846273252181305,
                "y": -0.010016228788490908,
                "z": 0.00042375368326794013,
                "w": 0.999561944383457
            }
        }
    },
    "1662572008325373938": {
        "pose": {
            "position": {
                "x": -0.10884600099193896,
                "y": -0.053910890571816,
                "z": -0.01986897387822002
            },
            "orientation": {
                "x": 0.02715820681590898,
                "y": -0.007949993320502334,
                "z": -0.0006465209618842934,
                "w": 0.9995993254396454
            }
        }
    },
    "1662572008385478780": {
        "pose": {
            "position": {
                "x": -0.09422057349510633,
                "y": -0.05173922319963454,
                "z": -0.01851268051027033
            },
            "orientation": {
                "x": 0.02563017617769599,
                "y": -0.006719855264874135,
                "z": 0.0006982397923160888,
                "w": 0.9996486633190241
            }
        }
    },
    "1662572008435560233": {
        "pose": {
            "position": {
                "x": -0.09841397445161609,
                "y": -0.06196423302586812,
                "z": -0.026164013796703346
            },
            "orientation": {
                "x": 0.031716769692969084,
                "y": -0.013572200545329219,
                "z": -0.0011913710730318816,
                "w": 0.9994040336758537
            }
        }
    },
    "1662572008475758435": {
        "pose": {
            "position": {
                "x": -0.07698623311953007,
                "y": -0.0518873601923211,
                "z": -0.01750305216804092
            },
            "orientation": {
                "x": 0.025916660607602886,
                "y": -0.008443203577994258,
                "z": -4.3223219184865004e-05,
                "w": 0.9996284495491532
            }
        }
    },
    "1662572008556278188": {
        "pose": {
            "position": {
                "x": -0.033879377955970624,
                "y": 0.01878098711841066,
                "z": -0.0029637687690378246
            },
            "orientation": {
                "x": -0.007923507697255871,
                "y": 0.006945607841683998,
                "z": 0.000233594624499655,
                "w": 0.9999444594531401
            }
        }
    },
    "1662572008639562339": {
        "acceleration": {
            "x": -0.00732421875,
            "y": -0.0068359375,
            "z": 1.0068359375
        }
    },
    "1662572008639579118": {
        "acceleration": {
            "x": -0.00732421875,
            "y": -0.0068359375,
            "z": 1.0068359375
        }
    },
    "1662572008653800804": {
        "acceleration": {
            "x": -0.00732421875,
            "y": -0.0068359375,
            "z": 1.0068359375
        }
    },
    "1662572008653844194": {
        "acceleration": {
            "x": -0.00732421875,
            "y": -0.0068359375,
            "z": 1.0068359375
        }
    },
    "1662572008689425254": {
        "acceleration": {
            "x": 0.0029296875,
            "y": -0.00390625,
            "z": 1.005859375
        }
    },
    "1662572008689464820": {
        "acceleration": {
            "x": 0.0029296875,
            "y": -0.00390625,
            "z": 1.005859375
        }
    },
    "1662572008703575979": {
        "acceleration": {
            "x": 0.0029296875,
            "y": -0.00390625,
            "z": 1.005859375
        }
    },
    "1662572008703613501": {
        "acceleration": {
            "x": 0.0029296875,
            "y": -0.00390625,
            "z": 1.005859375
        }
    },
    "1662572008739152654": {
        "acceleration": {
            "x": 0.0,
            "y": -0.03759765625,
            "z": 1.00927734375
        }
    },
    "1662572008739170928": {
        "acceleration": {
            "x": 0.0,
            "y": -0.03759765625,
            "z": 1.00927734375
        }
    },
    "1662572008753269298": {
        "acceleration": {
            "x": 0.0,
            "y": -0.03759765625,
            "z": 1.00927734375
        }
    },
    "1662572008753290106": {
        "acceleration": {
            "x": 0.0,
            "y": -0.03759765625,
            "z": 1.00927734375
        }
    },
    "1662572008716295064": {
        "pose": {
            "position": {
                "x": -0.013248654291068189,
                "y": -0.048362339211034874,
                "z": -0.01179687326108078
            },
            "orientation": {
                "x": 0.02464194829252541,
                "y": -0.0011921845505697126,
                "z": 0.0007584724635942154,
                "w": 0.9996953424918351
            }
        }
    },
    "1662572008789322518": {
        "acceleration": {
            "x": 0.001953125,
            "y": -0.07080078125,
            "z": 0.9912109375
        }
    },
    "1662572008789369676": {
        "acceleration": {
            "x": 0.001953125,
            "y": -0.07080078125,
            "z": 0.9912109375
        }
    },
    "1662572008803352404": {
        "acceleration": {
            "x": 0.001953125,
            "y": -0.07080078125,
            "z": 0.9912109375
        }
    },
    "1662572008803372344": {
        "acceleration": {
            "x": 0.001953125,
            "y": -0.07080078125,
            "z": 0.9912109375
        }
    },
    "1662572008756896607": {
        "pose": {
            "position": {
                "x": -0.003662740322796169,
                "y": -0.0733419028343135,
                "z": -0.020889576441635107
            },
            "orientation": {
                "x": 0.037136254306829056,
                "y": 0.00028219309115732846,
                "z": 0.0011222812094957887,
                "w": 0.9993095413674408
            }
        }
    },
    "1662572008838891931": {
        "acceleration": {
            "x": 0.01220703125,
            "y": -0.0458984375,
            "z": 1.00634765625
        }
    },
    "1662572008838912035": {
        "acceleration": {
            "x": 0.01220703125,
            "y": -0.0458984375,
            "z": 1.00634765625
        }
    },
    "1662572008852932814": {
        "acceleration": {
            "x": 0.01220703125,
            "y": -0.0458984375,
            "z": 1.00634765625
        }
    },
    "1662572008852981607": {
        "acceleration": {
            "x": 0.01220703125,
            "y": -0.0458984375,
            "z": 1.00634765625
        }
    },
    "1662572008888369352": {
        "acceleration": {
            "x": -0.00048828125,
            "y": -0.00634765625,
            "z": 1.0107421875
        }
    },
    "1662572008888397617": {
        "acceleration": {
            "x": -0.00048828125,
            "y": -0.00634765625,
            "z": 1.0107421875
        }
    },
    "1662572008903332663": {
        "acceleration": {
            "x": -0.00048828125,
            "y": -0.00634765625,
            "z": 1.0107421875
        }
    }
}