{
    "1662574399193293824": {
        "acceleration": {
            "x": 0.00244140625,
            "y": 0.0,
            "z": 1.00439453125
        }
    },
    "1662574399193321658": {
        "acceleration": {
            "x": 0.00244140625,
            "y": 0.0,
            "z": 1.00439453125
        }
    },
    "1662574399229122527": {
        "acceleration": {
            "x": 0.001953125,
            "y": 0.0,
            "z": 1.0048828125
        }
    },
    "1662574399229147289": {
        "acceleration": {
            "x": 0.001953125,
            "y": 0.0,
            "z": 1.0048828125
        }
    },
    "1662574399243267905": {
        "acceleration": {
            "x": 0.001953125,
            "y": 0.0,
            "z": 1.0048828125
        }
    },
    "1662574399243327988": {
        "acceleration": {
            "x": 0.001953125,
            "y": 0.0,
            "z": 1.0048828125
        }
    },
    "1662574399278919787": {
        "acceleration": {
            "x": 0.00390625,
            "y": 0.00830078125,
            "z": 1.00244140625
        }
    },
    "1662574399278934470": {
        "acceleration": {
            "x": 0.00390625,
            "y": 0.00830078125,
            "z": 1.00244140625
        }
    },
    "1662574399292866908": {
        "acceleration": {
            "x": 0.00390625,
            "y": 0.00830078125,
            "z": 1.00244140625
        }
    },
    "1662574399292891266": {
        "acceleration": {
            "x": 0.00390625,
            "y": 0.00830078125,
            "z": 1.00244140625
        }
    },
    "1662574399328572621": {
        "acceleration": {
            "x": -0.00244140625,
            "y": -0.02490234375,
            "z": 1.01025390625
        }
    },
    "1662574399328591668": {
        "acceleration": {
            "x": -0.00244140625,
            "y": -0.02490234375,
            "z": 1.01025390625
        }
    },
    "1662574399342814533": {
        "acceleration": {
            "x": -0.00244140625,
            "y": -0.02490234375,
            "z": 1.01025390625
        }
    },
    "1662574399342861293": {
        "acceleration": {
            "x": -0.00244140625,
            "y": -0.02490234375,
            "z": 1.01025390625
        }
    },
    "1662574399378008374": {
        "acceleration": {
            "x": -0.00146484375,
            "y": -0.01513671875,
            "z": 1.001953125
        }
    },
    "1662574399378023532": {
        "acceleration": {
            "x": -0.00146484375,
            "y": -0.01513671875,
            "z": 1.001953125
        }
    },
    "1662574399393124813": {
        "acceleration": {
            "x": -0.00146484375,
            "y": -0.01513671875,
            "z": 1.001953125
        }
    },
    "1662574399393143312": {
        "acceleration": {
            "x": -0.00146484375,
            "y": -0.01513671875,
            "z": 1.001953125
        }
    },
    "1662574399427923017": {
        "acceleration": {
            "x": 0.001953125,
            "y": 0.0126953125,
            "z": 1.00439453125
        }
    },
    "1662574399427940717": {
        "acceleration": {
            "x": 0.001953125,
            "y": 0.0126953125,
            "z": 1.00439453125
        }
    },
    "1662574399443024136": {
        "acceleration": {
            "x": 0.001953125,
            "y": 0.0126953125,
            "z": 1.00439453125
        }
    },
    "1662574399443047325": {
        "acceleration": {
            "x": 0.001953125,
            "y": 0.0126953125,
            "z": 1.00439453125
        }
    },
    "1662574399478613292": {
        "acceleration": {
            "x": 0.001953125,
            "y": 0.00927734375,
            "z": 1.00634765625
        }
    },
    "1662574399478640185": {
        "acceleration": {
            "x": 0.001953125,
            "y": 0.00927734375,
            "z": 1.00634765625
        }
    },
    "1662574399492469410": {
        "acceleration": {
            "x": 0.001953125,
            "y": 0.00927734375,
            "z": 1.00634765625
        }
    },
    "1662574399492498570": {
        "acceleration": {
            "x": 0.001953125,
            "y": 0.00927734375,
            "z": 1.00634765625
        }
    },
    "1662574399528008526": {
        "acceleration": {
            "x": -0.009765625,
            "y": 0.009765625,
            "z": 1.00341796875
        }
    },
    "1662574399528026540": {
        "acceleration": {
            "x": -0.009765625,
            "y": 0.009765625,
            "z": 1.00341796875
        }
    },
    "1662574399542442310": {
        "acceleration": {
            "x": -0.009765625,
            "y": 0.009765625,
            "z": 1.00341796875
        }
    },
    "1662574399542471377": {
        "acceleration": {
            "x": -0.009765625,
            "y": 0.009765625,
            "z": 1.00341796875
        }
    },
    "1662574399577945650": {
        "acceleration": {
            "x": 0.00048828125,
            "y": -0.005859375,
            "z": 1.00341796875
        }
    },
    "1662574399577963063": {
        "acceleration": {
            "x": 0.00048828125,
            "y": -0.005859375,
            "z": 1.00341796875
        }
    },
    "1662574399593133183": {
        "acceleration": {
            "x": 0.00048828125,
            "y": -0.005859375,
            "z": 1.00341796875
        }
    },
    "1662574399593152352": {
        "acceleration": {
            "x": 0.00048828125,
            "y": -0.005859375,
            "z": 1.00341796875
        }
    },
    "1662574399628604210": {
        "acceleration": {
            "x": 0.00244140625,
            "y": -0.00927734375,
            "z": 1.0078125
        }
    },
    "1662574399628627083": {
        "acceleration": {
            "x": 0.00244140625,
            "y": -0.00927734375,
            "z": 1.0078125
        }
    },
    "1662574399642795444": {
        "acceleration": {
            "x": 0.00244140625,
            "y": -0.00927734375,
            "z": 1.0078125
        }
    },
    "1662574399642847618": {
        "acceleration": {
            "x": 0.00244140625,
            "y": -0.00927734375,
            "z": 1.0078125
        }
    },
    "1662574399678438228": {
        "acceleration": {
            "x": 0.00341796875,
            "y": -0.0029296875,
            "z": 1.00341796875
        }
    },
    "1662574399678455344": {
        "acceleration": {
            "x": 0.00341796875,
            "y": -0.0029296875,
            "z": 1.00341796875
        }
    },
    "1662574399692557322": {
        "acceleration": {
            "x": 0.00341796875,
            "y": -0.0029296875,
            "z": 1.00341796875
        }
    },
    "1662574399692577477": {
        "acceleration": {
            "x": 0.00341796875,
            "y": -0.0029296875,
            "z": 1.00341796875
        }
    },
    "1662574399728023603": {
        "acceleration": {
            "x": 0.0029296875,
            "y": 0.0029296875,
            "z": 1.00390625
        }
    },
    "1662574399728040608": {
        "acceleration": {
            "x": 0.0029296875,
            "y": 0.0029296875,
            "z": 1.00390625
        }
    },
    "1662574399742094183": {
        "acceleration": {
            "x": 0.0029296875,
            "y": 0.0029296875,
            "z": 1.00390625
        }
    },
    "1662574399742122383": {
        "acceleration": {
            "x": 0.0029296875,
            "y": 0.0029296875,
            "z": 1.00390625
        }
    },
    "1662574399777880362": {
        "acceleration": {
            "x": 0.00146484375,
            "y": 0.00634765625,
            "z": 1.00244140625
        }
    },
    "1662574399777897114": {
        "acceleration": {
            "x": 0.00146484375,
            "y": 0.00634765625,
            "z": 1.00244140625
        }
    },
    "1662574399791933050": {
        "acceleration": {
            "x": 0.00146484375,
            "y": 0.00634765625,
            "z": 1.00244140625
        }
    },
    "1662574399791955320": {
        "acceleration": {
            "x": 0.00146484375,
            "y": 0.00634765625,
            "z": 1.00244140625
        }
    },
    "1662574399827380201": {
        "acceleration": {
            "x": 0.00048828125,
            "y": 0.01904296875,
            "z": 1.00048828125
        }
    },
    "1662574399827396538": {
        "acceleration": {
            "x": 0.00048828125,
            "y": 0.01904296875,
            "z": 1.00048828125
        }
    },
    "1662574399841756315": {
        "acceleration": {
            "x": 0.00048828125,
            "y": 0.01904296875,
            "z": 1.00048828125
        }
    },
    "1662574399841786149": {
        "acceleration": {
            "x": 0.00048828125,
            "y": 0.01904296875,
            "z": 1.00048828125
        }
    },
    "1662574399877431488": {
        "acceleration": {
            "x": 0.0029296875,
            "y": 0.00732421875,
            "z": 0.998046875
        }
    },
    "1662574399877465726": {
        "acceleration": {
            "x": 0.0029296875,
            "y": 0.00732421875,
            "z": 0.998046875
        }
    },
    "1662574399891479782": {
        "acceleration": {
            "x": 0.0029296875,
            "y": 0.00732421875,
            "z": 0.998046875
        }
    },
    "1662574399891505459": {
        "acceleration": {
            "x": 0.0029296875,
            "y": 0.00732421875,
            "z": 0.998046875
        }
    },
    "1662574399927231080": {
        "acceleration": {
            "x": 0.00146484375,
            "y": 0.00732421875,
            "z": 1.00537109375
        }
    },
    "1662574399927255846": {
        "acceleration": {
            "x": 0.00146484375,
            "y": 0.00732421875,
            "z": 1.00537109375
        }
    },
    "1662574399941550640": {
        "acceleration": {
            "x": 0.00146484375,
            "y": 0.00732421875,
            "z": 1.00537109375
        }
    },
    "1662574399941569253": {
        "acceleration": {
            "x": 0.00146484375,
            "y": 0.00732421875,
            "z": 1.00537109375
        }
    },
    "1662574399976932664": {
        "acceleration": {
            "x": 0.0,
            "y": 0.009765625,
            "z": 1.00146484375
        }
    },
    "1662574399976960264": {
        "acceleration": {
            "x": 0.0,
            "y": 0.009765625,
            "z": 1.00146484375
        }
    },
    "1662574399992034692": {
        "acceleration": {
            "x": 0.0,
            "y": 0.009765625,
            "z": 1.00146484375
        }
    },
    "1662574399992057974": {
        "acceleration": {
            "x": 0.0,
            "y": 0.009765625,
            "z": 1.00146484375
        }
    },
    "1662574400026660677": {
        "acceleration": {
            "x": 0.00048828125,
            "y": 0.0205078125,
            "z": 1.0029296875
        }
    },
    "1662574400026677511": {
        "acceleration": {
            "x": 0.00048828125,
            "y": 0.0205078125,
            "z": 1.0029296875
        }
    },
    "1662574400041774101": {
        "acceleration": {
            "x": 0.00048828125,
            "y": 0.0205078125,
            "z": 1.0029296875
        }
    },
    "1662574400041815896": {
        "acceleration": {
            "x": 0.00048828125,
            "y": 0.0205078125,
            "z": 1.0029296875
        }
    },
    "1662574400077447337": {
        "acceleration": {
            "x": -0.00244140625,
            "y": 0.021484375,
            "z": 1.0048828125
        }
    },
    "1662574400077470805": {
        "acceleration": {
            "x": -0.00244140625,
            "y": 0.021484375,
            "z": 1.0048828125
        }
    },
    "1662574400091859502": {
        "acceleration": {
            "x": -0.00244140625,
            "y": 0.021484375,
            "z": 1.0048828125
        }
    },
    "1662574400091891892": {
        "acceleration": {
            "x": -0.00244140625,
            "y": 0.021484375,
            "z": 1.0048828125
        }
    },
    "1662574400127389370": {
        "acceleration": {
            "x": -0.001953125,
            "y": 0.01904296875,
            "z": 1.005859375
        }
    },
    "1662574400127450335": {
        "acceleration": {
            "x": -0.001953125,
            "y": 0.01904296875,
            "z": 1.005859375
        }
    },
    "1662574400141389863": {
        "acceleration": {
            "x": -0.001953125,
            "y": 0.01904296875,
            "z": 1.005859375
        }
    },
    "1662574400141414756": {
        "acceleration": {
            "x": -0.001953125,
            "y": 0.01904296875,
            "z": 1.005859375
        }
    },
    "1662574400176777356": {
        "acceleration": {
            "x": 0.0048828125,
            "y": 0.0244140625,
            "z": 1.0078125
        }
    },
    "1662574400176797231": {
        "acceleration": {
            "x": 0.0048828125,
            "y": 0.0244140625,
            "z": 1.0078125
        }
    },
    "1662574400191180750": {
        "acceleration": {
            "x": 0.0048828125,
            "y": 0.0244140625,
            "z": 1.0078125
        }
    },
    "1662574400191199335": {
        "acceleration": {
            "x": 0.0048828125,
            "y": 0.0244140625,
            "z": 1.0078125
        }
    },
    "1662574399149981768": {
        "pose": {
            "position": {
                "x": 4.163336342344337e-17,
                "y": -2.0816681711721685e-17,
                "z": -1.1769631218849745e-34
            },
            "orientation": {
                "x": 3.512780301737418e-18,
                "y": -3.429046369620461e-19,
                "z": 4.565520209479604e-19,
                "w": 1.0
            }
        }
    },
    "1662574399190320329": {
        "pose": {
            "position": {
                "x": -0.0032413692668039574,
                "y": 0.00048079806738219086,
                "z": 3.499157244761731e-05
            },
            "orientation": {
                "x": -0.0003680486686816541,
                "y": -0.0015263007668018446,
                "z": -0.0003941902287225104,
                "w": 0.9999986897792469
            }
        }
    },
    "1662574399240670838": {
        "pose": {
            "position": {
                "x": -0.012286800946434556,
                "y": 0.0041958969707674865,
                "z": 0.0008986575331996459
            },
            "orientation": {
                "x": -0.0021936650672269857,
                "y": -0.00547085598553604,
                "z": -0.0011081586861320402,
                "w": 0.9999820146146051
            }
        }
    },
    "1662574399310914635": {
        "pose": {
            "position": {
                "x": -0.008571924762680027,
                "y": 0.007576183514482852,
                "z": -0.00412176209463481
            },
            "orientation": {
                "x": -0.0035892940461403552,
                "y": -0.002570948030842628,
                "z": -0.0010988285226965632,
                "w": 0.9999896498316125
            }
        }
    },
    "1662574399350999968": {
        "pose": {
            "position": {
                "x": -0.017250405251016305,
                "y": 0.006444408796477923,
                "z": -0.0007685259097575602
            },
            "orientation": {
                "x": -0.0033674368546250466,
                "y": -0.005761598580612413,
                "z": -0.0016299907625711891,
                "w": 0.9999764034620716
            }
        }
    },
    "1662574399391043264": {
        "pose": {
            "position": {
                "x": -0.010786763628912755,
                "y": -0.0012994703444477614,
                "z": -0.0038431087476593594
            },
            "orientation": {
                "x": 0.000200975065338666,
                "y": -0.0016568259922855532,
                "z": -0.0020503346685069525,
                "w": 0.9999965053260945
            }
        }
    },
    "1662574399431245525": {
        "pose": {
            "position": {
                "x": -0.03285106517864429,
                "y": 0.0006683693152207111,
                "z": -0.005450195565089772
            },
            "orientation": {
                "x": -0.0005749540025370466,
                "y": -0.0097813078117844,
                "z": -0.002830581853799901,
                "w": 0.9999479902733718
            }
        }
    },
    "1662574399481956368": {
        "pose": {
            "position": {
                "x": -0.021267009644584157,
                "y": 0.0035978797906170445,
                "z": -0.004345147440833864
            },
            "orientation": {
                "x": -0.002115167094349041,
                "y": -0.0028734067557914843,
                "z": -0.0016729896854629214,
                "w": 0.9999922353235005
            }
        }
    },
    "1662574399521700419": {
        "pose": {
            "position": {
                "x": -0.018868181420336815,
                "y": -0.006708954138309823,
                "z": -0.004897603527169283
            },
            "orientation": {
                "x": 0.003100124206153479,
                "y": 0.000842282643115097,
                "z": -0.001305242647348617,
                "w": 0.9999939880476717
            }
        }
    },
    "1662574399572107992": {
        "pose": {
            "position": {
                "x": -0.032848919686502394,
                "y": 0.0027925130314483066,
                "z": -0.0048648393444510555
            },
            "orientation": {
                "x": -0.001598275503550408,
                "y": -0.004821567043398609,
                "z": -0.001050383498422726,
                "w": 0.9999865472600954
            }
        }
    },
    "1662574399622091033": {
        "pose": {
            "position": {
                "x": -0.03210648329175588,
                "y": -0.008891596190532616,
                "z": -0.006617303132157537
            },
            "orientation": {
                "x": 0.004061997062229819,
                "y": -0.0018729056022954611,
                "z": -0.002016916095518856,
                "w": 0.9999879621545126
            }
        }
    },
    "1662574399692791302": {
        "pose": {
            "position": {
                "x": -0.02986870072942292,
                "y": -0.010121220517727379,
                "z": -0.008220442859718916
            },
            "orientation": {
                "x": 0.004754079935131393,
                "y": 0.0011358821578181702,
                "z": -0.001723094954652085,
                "w": 0.9999865696295483
            }
        }
    },
    "1662574399732739431": {
        "pose": {
            "position": {
                "x": -0.058732467914506196,
                "y": -0.007546931737427848,
                "z": -0.006183378218894828
            },
            "orientation": {
                "x": 0.003607281824772447,
                "y": -0.011579453685929067,
                "z": -0.0011396206918747396,
                "w": 0.9999257997645881
            }
        }
    },
    "1662574399772784323": {
        "pose": {
            "position": {
                "x": -0.037224601870712234,
                "y": -0.010791722026234551,
                "z": -0.008191950831272278
            },
            "orientation": {
                "x": 0.0047347203483502605,
                "y": -0.0007236931459800391,
                "z": -0.0022066549317114434,
                "w": 0.9999860945860527
            }
        }
    },
    "1662574399822901526": {
        "pose": {
            "position": {
                "x": -0.02837001313117813,
                "y": -0.025650587734800775,
                "z": -0.006733342787795057
            },
            "orientation": {
                "x": 0.012148236223398938,
                "y": 0.003667477991431818,
                "z": 0.0008420744083805095,
                "w": 0.9999191271660592
            }
        }
    },
    "1662574399863098098": {
        "pose": {
            "position": {
                "x": -0.02363372890799955,
                "y": -0.028149229767151843,
                "z": -0.007313019872467118
            },
            "orientation": {
                "x": 0.013378686359362674,
                "y": 0.005880392608122903,
                "z": 0.0010764155309519006,
                "w": 0.9998926307677625
            }
        }
    },
    "1662574399913713701": {
        "pose": {
            "position": {
                "x": -0.03982125093871895,
                "y": -0.00844688130543824,
                "z": -0.006796845428210779
            },
            "orientation": {
                "x": 0.00363336990083208,
                "y": -0.002231848190467483,
                "z": -0.0017859280274477637,
                "w": 0.9999893139118534
            }
        }
    },
    "1662574399953616640": {
        "pose": {
            "position": {
                "x": -0.017567894295504406,
                "y": -0.02060255221231592,
                "z": -0.006130967450891562
            },
            "orientation": {
                "x": 0.009450139894028424,
                "y": 0.007614641338371303,
                "z": 0.00018868944671111428,
                "w": 0.9999263355315551
            }
        }
    },
    "1662574400226699221": {
        "acceleration": {
            "x": 0.0009765625,
            "y": 0.01171875,
            "z": 1.00390625
        }
    },
    "1662574400226723484": {
        "acceleration": {
            "x": 0.0009765625,
            "y": 0.01171875,
            "z": 1.00390625
        }
    },
    "1662574399993700171": {
        "pose": {
            "position": {
                "x": -0.05289287208699325,
                "y": 0.003414846911078569,
                "z": -0.004180943485112393
            },
            "orientation": {
                "x": -0.0015825484311294167,
                "y": -0.010622614048177948,
                "z": -0.00010251291848470092,
                "w": 0.9999423208877342
            }
        }
    },
    "1662574400033783917": {
        "pose": {
            "position": {
                "x": -0.03414602469265752,
                "y": -0.007518915820875128,
                "z": -0.0063236434948005975
            },
            "orientation": {
                "x": 0.0036584540670427197,
                "y": -0.002640376476171311,
                "z": -0.001076770319729165,
                "w": 0.9999892422879268
            }
        }
    },
    "1662574400104430558": {
        "pose": {
            "position": {
                "x": -0.03800561044000873,
                "y": 0.0017292343020457522,
                "z": -0.003941716265789363
            },
            "orientation": {
                "x": -0.0013126785641897865,
                "y": -0.007748100997606454,
                "z": -0.0005804771936686795,
                "w": 0.999968952944113
            }
        }
    },
    "1662574400144294486": {
        "pose": {
            "position": {
                "x": -0.027756871636867842,
                "y": -0.01284571222981309,
                "z": -0.004447421811512786
            },
            "orientation": {
                "x": 0.0057132477585322555,
                "y": -0.002964731344508527,
                "z": -0.002231103512391295,
                "w": 0.9999767954033841
            }
        }
    },
    "1662574400240678922": {
        "acceleration": {
            "x": 0.0009765625,
            "y": 0.01171875,
            "z": 1.00390625
        }
    },
    "1662574400240724370": {
        "acceleration": {
            "x": 0.0009765625,
            "y": 0.01171875,
            "z": 1.00390625
        }
    },
    "1662574400194758131": {
        "pose": {
            "position": {
                "x": -0.023876921333482445,
                "y": -0.0005621709203663357,
                "z": -0.0032263145769555763
            },
            "orientation": {
                "x": -0.00024867953989878244,
                "y": -0.004383082078330098,
                "z": -0.001579359676589651,
                "w": 0.9999891161272672
            }
        }
    },
    "1662574400276050166": {
        "acceleration": {
            "x": 0.001953125,
            "y": -0.01416015625,
            "z": 1.00341796875
        }
    },
    "1662574400276082850": {
        "acceleration": {
            "x": 0.001953125,
            "y": -0.01416015625,
            "z": 1.00341796875
        }
    },
    "1662574400290181251": {
        "acceleration": {
            "x": 0.001953125,
            "y": -0.01416015625,
            "z": 1.00341796875
        }
    },
    "1662574400290201831": {
        "acceleration": {
            "x": 0.001953125,
            "y": -0.01416015625,
            "z": 1.00341796875
        }
    },
    "1662574400325701544": {
        "acceleration": {
            "x": 0.0078125,
            "y": -0.0126953125,
            "z": 1.0029296875
        }
    },
    "1662574400325737740": {
        "acceleration": {
            "x": 0.0078125,
            "y": -0.0126953125,
            "z": 1.0029296875
        }
    },
    "1662574400340859193": {
        "acceleration": {
            "x": 0.0078125,
            "y": -0.0126953125,
            "z": 1.0029296875
        }
    },
    "1662574400340886925": {
        "acceleration": {
            "x": 0.0078125,
            "y": -0.0126953125,
            "z": 1.0029296875
        }
    },
    "1662574400376367697": {
        "acceleration": {
            "x": 0.00146484375,
            "y": -0.013671875,
            "z": 1.001953125
        }
    },
    "1662574400376395577": {
        "acceleration": {
            "x": 0.00146484375,
            "y": -0.013671875,
            "z": 1.001953125
        }
    },
    "1662574400390488525": {
        "acceleration": {
            "x": 0.00146484375,
            "y": -0.013671875,
            "z": 1.001953125
        }
    },
    "1662574400390541266": {
        "acceleration": {
            "x": 0.00146484375,
            "y": -0.013671875,
            "z": 1.001953125
        }
    },
    "1662574400426358440": {
        "acceleration": {
            "x": 0.00244140625,
            "y": -0.01904296875,
            "z": 1.001953125
        }
    },
    "1662574400426384549": {
        "acceleration": {
            "x": 0.00244140625,
            "y": -0.01904296875,
            "z": 1.001953125
        }
    },
    "1662574400440756022": {
        "acceleration": {
            "x": 0.00244140625,
            "y": -0.01904296875,
            "z": 1.001953125
        }
    },
    "1662574400440778997": {
        "acceleration": {
            "x": 0.00244140625,
            "y": -0.01904296875,
            "z": 1.001953125
        }
    }
}