{
    "1662573343804907567": {
        "acceleration": {
            "x": 0.001953125,
            "y": 0.0,
            "z": 1.00341796875
        }
    },
    "1662573343804938292": {
        "acceleration": {
            "x": 0.001953125,
            "y": 0.0,
            "z": 1.00341796875
        }
    },
    "1662573343840336763": {
        "acceleration": {
            "x": 0.00146484375,
            "y": 0.0,
            "z": 1.0029296875
        }
    },
    "1662573343840351482": {
        "acceleration": {
            "x": 0.00146484375,
            "y": 0.0,
            "z": 1.0029296875
        }
    },
    "1662573343854338114": {
        "acceleration": {
            "x": 0.00146484375,
            "y": 0.0,
            "z": 1.0029296875
        }
    },
    "1662573343854361218": {
        "acceleration": {
            "x": 0.00146484375,
            "y": 0.0,
            "z": 1.0029296875
        }
    },
    "1662573343889943251": {
        "acceleration": {
            "x": -0.04052734375,
            "y": -0.43017578125,
            "z": 1.0048828125
        }
    },
    "1662573343889960419": {
        "acceleration": {
            "x": -0.04052734375,
            "y": -0.43017578125,
            "z": 1.0048828125
        }
    },
    "1662573343904274960": {
        "acceleration": {
            "x": -0.04052734375,
            "y": -0.43017578125,
            "z": 1.0048828125
        }
    },
    "1662573343904296049": {
        "acceleration": {
            "x": -0.04052734375,
            "y": -0.43017578125,
            "z": 1.0048828125
        }
    },
    "1662573343939903316": {
        "acceleration": {
            "x": 0.0146484375,
            "y": -0.10888671875,
            "z": 1.02978515625
        }
    },
    "1662573343939928012": {
        "acceleration": {
            "x": 0.0146484375,
            "y": -0.10888671875,
            "z": 1.02978515625
        }
    },
    "1662573343953956777": {
        "acceleration": {
            "x": 0.0146484375,
            "y": -0.10888671875,
            "z": 1.02978515625
        }
    },
    "1662573343954005816": {
        "acceleration": {
            "x": 0.0146484375,
            "y": -0.10888671875,
            "z": 1.02978515625
        }
    },
    "1662573343989579279": {
        "acceleration": {
            "x": -0.0205078125,
            "y": -0.0390625,
            "z": 1.01513671875
        }
    },
    "1662573343989601597": {
        "acceleration": {
            "x": -0.0205078125,
            "y": -0.0390625,
            "z": 1.01513671875
        }
    },
    "1662573344003774005": {
        "acceleration": {
            "x": -0.0205078125,
            "y": -0.0390625,
            "z": 1.01513671875
        }
    },
    "1662573344003796196": {
        "acceleration": {
            "x": -0.0205078125,
            "y": -0.0390625,
            "z": 1.01513671875
        }
    },
    "1662573344039473180": {
        "acceleration": {
            "x": -0.00634765625,
            "y": -0.0087890625,
            "z": 1.01904296875
        }
    },
    "1662573344039510358": {
        "acceleration": {
            "x": -0.00634765625,
            "y": -0.0087890625,
            "z": 1.01904296875
        }
    },
    "1662573344053411890": {
        "acceleration": {
            "x": -0.00634765625,
            "y": -0.0087890625,
            "z": 1.01904296875
        }
    },
    "1662573344053431072": {
        "acceleration": {
            "x": -0.00634765625,
            "y": -0.0087890625,
            "z": 1.01904296875
        }
    },
    "1662573344088732995": {
        "acceleration": {
            "x": -0.00439453125,
            "y": 0.142578125,
            "z": 0.98193359375
        }
    },
    "1662573344088750336": {
        "acceleration": {
            "x": -0.00439453125,
            "y": 0.142578125,
            "z": 0.98193359375
        }
    },
    "1662573344103866391": {
        "acceleration": {
            "x": -0.00439453125,
            "y": 0.142578125,
            "z": 0.98193359375
        }
    },
    "1662573344103884777": {
        "acceleration": {
            "x": -0.00439453125,
            "y": 0.142578125,
            "z": 0.98193359375
        }
    },
    "1662573344139288204": {
        "acceleration": {
            "x": -0.00146484375,
            "y": 0.39013671875,
            "z": 1.015625
        }
    },
    "1662573344139316693": {
        "acceleration": {
            "x": -0.00146484375,
            "y": 0.39013671875,
            "z": 1.015625
        }
    },
    "1662573344153324362": {
        "acceleration": {
            "x": -0.00146484375,
            "y": 0.39013671875,
            "z": 1.015625
        }
    },
    "1662573344153357259": {
        "acceleration": {
            "x": -0.00146484375,
            "y": 0.39013671875,
            "z": 1.015625
        }
    },
    "1662573344189299845": {
        "acceleration": {
            "x": -0.0009765625,
            "y": 0.5322265625,
            "z": 1.00927734375
        }
    },
    "1662573344189316347": {
        "acceleration": {
            "x": -0.0009765625,
            "y": 0.5322265625,
            "z": 1.00927734375
        }
    },
    "1662573344203421221": {
        "acceleration": {
            "x": -0.0009765625,
            "y": 0.5322265625,
            "z": 1.00927734375
        }
    },
    "1662573344203440401": {
        "acceleration": {
            "x": -0.0009765625,
            "y": 0.5322265625,
            "z": 1.00927734375
        }
    },
    "1662573344239057665": {
        "acceleration": {
            "x": 0.00537109375,
            "y": 0.19287109375,
            "z": 0.962890625
        }
    },
    "1662573344239073962": {
        "acceleration": {
            "x": 0.00537109375,
            "y": 0.19287109375,
            "z": 0.962890625
        }
    },
    "1662573344253074195": {
        "acceleration": {
            "x": 0.00537109375,
            "y": 0.19287109375,
            "z": 0.962890625
        }
    },
    "1662573344253114168": {
        "acceleration": {
            "x": 0.00537109375,
            "y": 0.19287109375,
            "z": 0.962890625
        }
    },
    "1662573344287916133": {
        "acceleration": {
            "x": 0.0029296875,
            "y": 0.0791015625,
            "z": 0.99853515625
        }
    },
    "1662573344287936954": {
        "acceleration": {
            "x": 0.0029296875,
            "y": 0.0791015625,
            "z": 0.99853515625
        }
    },
    "1662573344303124948": {
        "acceleration": {
            "x": 0.0029296875,
            "y": 0.0791015625,
            "z": 0.99853515625
        }
    },
    "1662573344303148268": {
        "acceleration": {
            "x": 0.0029296875,
            "y": 0.0791015625,
            "z": 0.99853515625
        }
    },
    "1662573344338494887": {
        "acceleration": {
            "x": -0.00048828125,
            "y": -0.0166015625,
            "z": 0.99462890625
        }
    },
    "1662573344338510306": {
        "acceleration": {
            "x": -0.00048828125,
            "y": -0.0166015625,
            "z": 0.99462890625
        }
    },
    "1662573344352574595": {
        "acceleration": {
            "x": -0.00048828125,
            "y": -0.0166015625,
            "z": 0.99462890625
        }
    },
    "1662573344352596488": {
        "acceleration": {
            "x": -0.00048828125,
            "y": -0.0166015625,
            "z": 0.99462890625
        }
    },
    "1662573344388137914": {
        "acceleration": {
            "x": -0.00537109375,
            "y": -0.1240234375,
            "z": 1.01708984375
        }
    },
    "1662573344388162714": {
        "acceleration": {
            "x": -0.00537109375,
            "y": -0.1240234375,
            "z": 1.01708984375
        }
    },
    "1662573344402268963": {
        "acceleration": {
            "x": -0.00537109375,
            "y": -0.1240234375,
            "z": 1.01708984375
        }
    },
    "1662573344402287450": {
        "acceleration": {
            "x": -0.00537109375,
            "y": -0.1240234375,
            "z": 1.01708984375
        }
    },
    "1662573344438061531": {
        "acceleration": {
            "x": 0.0,
            "y": -0.22607421875,
            "z": 0.99267578125
        }
    },
    "1662573344438089325": {
        "acceleration": {
            "x": 0.0,
            "y": -0.22607421875,
            "z": 0.99267578125
        }
    }
}